.gitignore
.travis.yml
LICENSE
MANIFEST.in
README.rst
bootstrap.py
buildout.cfg
setup.py
docs/CHANGES.rst
docs/code-documentation.rst
docs/commandline-api.rst
docs/conf.py
docs/credits.rst
docs/development.rst
docs/index.rst
docs/screenshot.gif
programslice/__init__.py
programslice/formatter.py
programslice/graph.py
programslice/package.py
programslice/visitor.py
programslice.egg-info/PKG-INFO
programslice.egg-info/SOURCES.txt
programslice.egg-info/dependency_links.txt
programslice.egg-info/entry_points.txt
programslice.egg-info/not-zip-safe
programslice.egg-info/requires.txt
programslice.egg-info/top_level.txt
programslice/tests/__init__.py
programslice/tests/conftest.py
programslice/tests/test_commandline.py
programslice/tests/test_graph.py
programslice/tests/test_slice_forward.txt
programslice/tests/test_visitor.py
programslice/tests/testdata/binsearch.py
programslice/tests/testdata/function.py
programslice/tests/testdata/overlapping.py