Metadata-Version: 1.1
Name: programslice
Version: 0.3.1
Summary: Static analysis tool for python
Home-page: https://github.com/romanofski/programslice
Author: Róman Joost
Author-email: roman@bromeco.de
License: GPLv3
Keywords: static analysis
Platform: UNKNOWN
Classifier: Environment :: Console
Classifier: Intended Audience :: Developers
Classifier: License :: OSI Approved :: GNU General Public License (GPL)
Classifier: Programming Language :: Python
Classifier: Programming Language :: Python :: 2.7
Classifier: Topic :: Software Development
